mFractal/__init__.py
mFractal/chj.py
mFractal/sigmoid_std.py
tests/__init__.py
tests/test_chj.py
mFractal-0.0.1a2.dist-info/LICENSE
mFractal-0.0.1a2.dist-info/METADATA
mFractal-0.0.1a2.dist-info/WHEEL
mFractal-0.0.1a2.dist-info/top_level.txt
mFractal-0.0.1a2.dist-info/RECORD
