Metadata-Version: 2.1
Name: mFractal
Version: 0.0.1a2
Home-page: https://github.com/lucasfr/mFractal
Author: Lucas G. S. França, Yujiang Wang, José G V Miranda
Author-email: lucas.franca@northumbria.ac.uk
Classifier: Programming Language :: Python :: 3
Classifier: License :: OSI Approved :: MIT License
Classifier: Operating System :: OS Independent
Requires-Python: >=3.8
License-File: LICENSE
